mycroft/__init__.py
mycroft/version.py
mycroft/skills/__init__.py
mycroft/skills/common_play_skill.py
mycroft_legacy-0.1.1.dist-info/LICENSE
mycroft_legacy-0.1.1.dist-info/METADATA
mycroft_legacy-0.1.1.dist-info/WHEEL
mycroft_legacy-0.1.1.dist-info/top_level.txt
mycroft_legacy-0.1.1.dist-info/zip-safe
mycroft_legacy-0.1.1.dist-info/RECORD
