Metadata-Version: 2.1
Name: mycroft-legacy
Version: 0.1.1
Summary: UNKNOWN
Home-page: https://github.com/OpenVoiceOS/mycroft-legacy
Author: jarbasai
Author-email: jarbasai@mailfence.com
License: apache-2.0
Platform: UNKNOWN
Classifier: Development Status :: 3 - Alpha
Classifier: Intended Audience :: Developers
Classifier: Topic :: Text Processing :: Linguistic
Classifier: License :: OSI Approved :: Apache Software License
Classifier: Programming Language :: Python :: 3.4
Classifier: Programming Language :: Python :: 3.5
Classifier: Programming Language :: Python :: 3.6
Requires-Dist: ovos-workshop
Requires-Dist: ovos-bus-client
